meshcutter/__init__.py
meshcutter/cli/__init__.py
meshcutter/cli/meshcut.py
meshcutter/core/__init__.py
meshcutter/core/boolean.py
meshcutter/core/constants.py
meshcutter/core/cq_cutter.py
meshcutter/core/cq_utils.py
meshcutter/core/cutter.py
meshcutter/core/detection.py
meshcutter/core/foot_cutter.py
meshcutter/core/geometry.py
meshcutter/core/grid.py
meshcutter/core/grid_utils.py
meshcutter/core/mesh_utils.py
meshcutter/core/profile.py
meshcutter/core/replace_base.py
meshcutter/core/validation.py
meshcutter/io/__init__.py
meshcutter/io/exporter.py
meshcutter/io/loader.py
meshcutter/tests/test_cq_cutter.py
microfinity/__init__.py
microfinity/calibration/__init__.py
microfinity/calibration/test_prints.py
microfinity/core/__init__.py
microfinity/core/base.py
microfinity/core/constants.py
microfinity/core/export.py
microfinity/core/helpers.py
microfinity/parts/__init__.py
microfinity/parts/baseplate.py
microfinity/parts/baseplate_layout.py
microfinity/parts/box.py
microfinity/parts/drawer.py
microfinity/scripts/__init__.py
microfinity/scripts/baseplate.py
microfinity/scripts/baseplate_layout.py
microfinity/scripts/box.py
microfinity/scripts/calibrate.py
microfinity-1.3.0.dist-info/licenses/LICENSE
microfinity-1.3.0.dist-info/METADATA
microfinity-1.3.0.dist-info/WHEEL
microfinity-1.3.0.dist-info/entry_points.txt
microfinity-1.3.0.dist-info/top_level.txt
microfinity-1.3.0.dist-info/RECORD
