Metadata-Version: 2.4
Name: microfinity
Version: 1.3.0
Summary: A python library to make Gridfinity compatible objects with CadQuery.
Author-email: Michael Gale <michael@fxbricks.com>
License: MIT
Project-URL: Homepage, https://github.com/nullstack65/microfinity
Project-URL: Repository, https://github.com/nullstack65/microfinity
Classifier: Development Status :: 4 - Beta
Classifier: Natural Language :: English
Classifier: Operating System :: OS Independent
Classifier: Programming Language :: Python :: 3.9
Classifier: Programming Language :: Python :: 3.10
Classifier: Programming Language :: Python :: 3.11
Classifier: Programming Language :: Python :: 3.12
Classifier: Intended Audience :: Developers
Classifier: License :: OSI Approved :: MIT License
Requires-Python: >=3.9
License-File: LICENSE
Requires-Dist: cadquery
Requires-Dist: cqkit>=0.5.6
Requires-Dist: trimesh>=4.0
Requires-Dist: shapely>=2.0
Requires-Dist: numpy
Requires-Dist: scipy
Requires-Dist: mapbox-earcut
Requires-Dist: networkx
Provides-Extra: dev
Requires-Dist: pytest; extra == "dev"
Requires-Dist: pytest-cov; extra == "dev"
Requires-Dist: black; extra == "dev"
Requires-Dist: flake8; extra == "dev"
Requires-Dist: commitizen; extra == "dev"
Provides-Extra: manifold
Requires-Dist: manifold3d>=2.3; extra == "manifold"
Provides-Extra: meshlab
Requires-Dist: pymeshlab>=2023.12; extra == "meshlab"
Provides-Extra: meshcutter
Requires-Dist: manifold3d>=2.3; extra == "meshcutter"
Dynamic: license-file
